odoo/addons/coupon_mass_mailing/README.rst
odoo/addons/coupon_mass_mailing/__init__.py
odoo/addons/coupon_mass_mailing/__manifest__.py
odoo/addons/coupon_mass_mailing/i18n/coupon_mass_mailing.pot
odoo/addons/coupon_mass_mailing/i18n/es.po
odoo/addons/coupon_mass_mailing/models/__init__.py
odoo/addons/coupon_mass_mailing/models/mailing_mailing.py
odoo/addons/coupon_mass_mailing/models/sale_coupon_program.py
odoo/addons/coupon_mass_mailing/readme/CONTRIBUTORS.rst
odoo/addons/coupon_mass_mailing/readme/DESCRIPTION.rst
odoo/addons/coupon_mass_mailing/static/description/icon.png
odoo/addons/coupon_mass_mailing/static/description/index.html
odoo/addons/coupon_mass_mailing/tests/__init__.py
odoo/addons/coupon_mass_mailing/tests/test_sale_coupon.py
odoo/addons/coupon_mass_mailing/views/mailing_mailing_view.xml
odoo/addons/coupon_mass_mailing/views/sale_coupon_program_view.xml
odoo_addon_coupon_mass_mailing-15.0.1.0.0.5.dist-info/METADATA
odoo_addon_coupon_mass_mailing-15.0.1.0.0.5.dist-info/WHEEL
odoo_addon_coupon_mass_mailing-15.0.1.0.0.5.dist-info/top_level.txt
odoo_addon_coupon_mass_mailing-15.0.1.0.0.5.dist-info/RECORD
